[
  {
    "id": 811,
    "created_at": "2023-05-02T19:39:05.000000Z",
    "updated_at": "2023-05-02T19:39:05.000000Z",
    "name": "Alburquerque",
    "code": "0701201000",
    "zip_code": "",
    "district": "Lone",
    "type": "Mun",
    "region_id": 8,
    "province_id": 39
  },
  {
    "id": 812,
    "created_at": "2023-05-02T19:39:05.000000Z",
    "updated_at": "2023-05-02T19:39:05.000000Z",
    "name": "Alicia",
    "code": "0701202000",
    "zip_code": "",
    "district": "Lone",
    "type": "Mun",
    "region_id": 8,
    "province_id": 39
  },
  {
    "id": 813,
    "created_at": "2023-05-02T19:39:05.000000Z",
    "updated_at": "2023-05-02T19:39:05.000000Z",
    "name": "Anda",
    "code": "0701203000",
    "zip_code": "",
    "district": "Lone",
    "type": "Mun",
    "region_id": 8,
    "province_id": 39
  },
  {
    "id": 814,
    "created_at": "2023-05-02T19:39:05.000000Z",
    "updated_at": "2023-05-02T19:39:05.000000Z",
    "name": "Antequera",
    "code": "0701204000",
    "zip_code": "",
    "district": "Lone",
    "type": "Mun",
    "region_id": 8,
    "province_id": 39
  },
  {
    "id": 815,
    "created_at": "2023-05-02T19:39:05.000000Z",
    "updated_at": "2023-05-02T19:39:05.000000Z",
    "name": "Baclayon",
    "code": "0701205000",
    "zip_code": "",
    "district": "Lone",
    "type": "Mun",
    "region_id": 8,
    "province_id": 39
  },
  {
    "id": 816,
    "created_at": "2023-05-02T19:39:05.000000Z",
    "updated_at": "2023-05-02T19:39:05.000000Z",
    "name": "Balilihan",
    "code": "0701206000",
    "zip_code": "",
    "district": "Lone",
    "type": "Mun",
    "region_id": 8,
    "province_id": 39
  },
  {
    "id": 817,
    "created_at": "2023-05-02T19:39:05.000000Z",
    "updated_at": "2023-05-02T19:39:05.000000Z",
    "name": "Batuan",
    "code": "0701207000",
    "zip_code": "",
    "district": "Lone",
    "type": "Mun",
    "region_id": 8,
    "province_id": 39
  },
  {
    "id": 818,
    "created_at": "2023-05-02T19:39:05.000000Z",
    "updated_at": "2023-05-02T19:39:05.000000Z",
    "name": "Bilar",
    "code": "0701208000",
    "zip_code": "",
    "district": "Lone",
    "type": "Mun",
    "region_id": 8,
    "province_id": 39
  },
  {
    "id": 819,
    "created_at": "2023-05-02T19:39:05.000000Z",
    "updated_at": "2023-05-02T19:39:05.000000Z",
    "name": "Buenavista",
    "code": "0701209000",
    "zip_code": "",
    "district": "Lone",
    "type": "Mun",
    "region_id": 8,
    "province_id": 39
  },
  {
    "id": 820,
    "created_at": "2023-05-02T19:39:05.000000Z",
    "updated_at": "2023-05-02T19:39:05.000000Z",
    "name": "Calape",
    "code": "0701210000",
    "zip_code": "",
    "district": "Lone",
    "type": "Mun",
    "region_id": 8,
    "province_id": 39
  },
  {
    "id": 821,
    "created_at": "2023-05-02T19:39:05.000000Z",
    "updated_at": "2023-05-02T19:39:05.000000Z",
    "name": "Candijay",
    "code": "0701211000",
    "zip_code": "",
    "district": "Lone",
    "type": "Mun",
    "region_id": 8,
    "province_id": 39
  },
  {
    "id": 822,
    "created_at": "2023-05-02T19:39:05.000000Z",
    "updated_at": "2023-05-02T19:39:05.000000Z",
    "name": "Carmen",
    "code": "0701212000",
    "zip_code": "",
    "district": "Lone",
    "type": "Mun",
    "region_id": 8,
    "province_id": 39
  },
  {
    "id": 823,
    "created_at": "2023-05-02T19:39:05.000000Z",
    "updated_at": "2023-05-02T19:39:05.000000Z",
    "name": "Catigbian",
    "code": "0701213000",
    "zip_code": "",
    "district": "Lone",
    "type": "Mun",
    "region_id": 8,
    "province_id": 39
  },
  {
    "id": 824,
    "created_at": "2023-05-02T19:39:05.000000Z",
    "updated_at": "2023-05-02T19:39:05.000000Z",
    "name": "Clarin",
    "code": "0701214000",
    "zip_code": "",
    "district": "Lone",
    "type": "Mun",
    "region_id": 8,
    "province_id": 39
  },
  {
    "id": 825,
    "created_at": "2023-05-02T19:39:05.000000Z",
    "updated_at": "2023-05-02T19:39:05.000000Z",
    "name": "Corella",
    "code": "0701215000",
    "zip_code": "",
    "district": "Lone",
    "type": "Mun",
    "region_id": 8,
    "province_id": 39
  },
  {
    "id": 826,
    "created_at": "2023-05-02T19:39:05.000000Z",
    "updated_at": "2023-05-02T19:39:05.000000Z",
    "name": "Cortes",
    "code": "0701216000",
    "zip_code": "",
    "district": "Lone",
    "type": "Mun",
    "region_id": 8,
    "province_id": 39
  },
  {
    "id": 827,
    "created_at": "2023-05-02T19:39:05.000000Z",
    "updated_at": "2023-05-02T19:39:05.000000Z",
    "name": "Dagohoy",
    "code": "0701217000",
    "zip_code": "",
    "district": "Lone",
    "type": "Mun",
    "region_id": 8,
    "province_id": 39
  },
  {
    "id": 828,
    "created_at": "2023-05-02T19:39:05.000000Z",
    "updated_at": "2023-05-02T19:39:05.000000Z",
    "name": "Danao",
    "code": "0701218000",
    "zip_code": "",
    "district": "Lone",
    "type": "Mun",
    "region_id": 8,
    "province_id": 39
  },
  {
    "id": 829,
    "created_at": "2023-05-02T19:39:05.000000Z",
    "updated_at": "2023-05-02T19:39:05.000000Z",
    "name": "Dauis",
    "code": "0701219000",
    "zip_code": "",
    "district": "Lone",
    "type": "Mun",
    "region_id": 8,
    "province_id": 39
  },
  {
    "id": 830,
    "created_at": "2023-05-02T19:39:05.000000Z",
    "updated_at": "2023-05-02T19:39:05.000000Z",
    "name": "Dimiao",
    "code": "0701220000",
    "zip_code": "",
    "district": "Lone",
    "type": "Mun",
    "region_id": 8,
    "province_id": 39
  },
  {
    "id": 831,
    "created_at": "2023-05-02T19:39:05.000000Z",
    "updated_at": "2023-05-02T19:39:05.000000Z",
    "name": "Duero",
    "code": "0701221000",
    "zip_code": "",
    "district": "Lone",
    "type": "Mun",
    "region_id": 8,
    "province_id": 39
  },
  {
    "id": 832,
    "created_at": "2023-05-02T19:39:05.000000Z",
    "updated_at": "2023-05-02T19:39:05.000000Z",
    "name": "Garcia Hernandez",
    "code": "0701222000",
    "zip_code": "",
    "district": "Lone",
    "type": "Mun",
    "region_id": 8,
    "province_id": 39
  },
  {
    "id": 833,
    "created_at": "2023-05-02T19:39:05.000000Z",
    "updated_at": "2023-05-02T19:39:05.000000Z",
    "name": "Guindulman",
    "code": "0701223000",
    "zip_code": "",
    "district": "Lone",
    "type": "Mun",
    "region_id": 8,
    "province_id": 39
  },
  {
    "id": 834,
    "created_at": "2023-05-02T19:39:05.000000Z",
    "updated_at": "2023-05-02T19:39:05.000000Z",
    "name": "Inabanga",
    "code": "0701224000",
    "zip_code": "",
    "district": "Lone",
    "type": "Mun",
    "region_id": 8,
    "province_id": 39
  },
  {
    "id": 835,
    "created_at": "2023-05-02T19:39:06.000000Z",
    "updated_at": "2023-05-02T19:39:06.000000Z",
    "name": "Jagna",
    "code": "0701225000",
    "zip_code": "",
    "district": "Lone",
    "type": "Mun",
    "region_id": 8,
    "province_id": 39
  },
  {
    "id": 836,
    "created_at": "2023-05-02T19:39:06.000000Z",
    "updated_at": "2023-05-02T19:39:06.000000Z",
    "name": "Getafe",
    "code": "0701226000",
    "zip_code": "",
    "district": "Lone",
    "type": "Mun",
    "region_id": 8,
    "province_id": 39
  },
  {
    "id": 837,
    "created_at": "2023-05-02T19:39:06.000000Z",
    "updated_at": "2023-05-02T19:39:06.000000Z",
    "name": "Lila",
    "code": "0701227000",
    "zip_code": "",
    "district": "Lone",
    "type": "Mun",
    "region_id": 8,
    "province_id": 39
  },
  {
    "id": 838,
    "created_at": "2023-05-02T19:39:06.000000Z",
    "updated_at": "2023-05-02T19:39:06.000000Z",
    "name": "Loay",
    "code": "0701228000",
    "zip_code": "",
    "district": "Lone",
    "type": "Mun",
    "region_id": 8,
    "province_id": 39
  },
  {
    "id": 839,
    "created_at": "2023-05-02T19:39:06.000000Z",
    "updated_at": "2023-05-02T19:39:06.000000Z",
    "name": "Loboc",
    "code": "0701229000",
    "zip_code": "",
    "district": "Lone",
    "type": "Mun",
    "region_id": 8,
    "province_id": 39
  },
  {
    "id": 840,
    "created_at": "2023-05-02T19:39:06.000000Z",
    "updated_at": "2023-05-02T19:39:06.000000Z",
    "name": "Loon",
    "code": "0701230000",
    "zip_code": "",
    "district": "Lone",
    "type": "Mun",
    "region_id": 8,
    "province_id": 39
  },
  {
    "id": 841,
    "created_at": "2023-05-02T19:39:06.000000Z",
    "updated_at": "2023-05-02T19:39:06.000000Z",
    "name": "Mabini",
    "code": "0701231000",
    "zip_code": "",
    "district": "Lone",
    "type": "Mun",
    "region_id": 8,
    "province_id": 39
  },
  {
    "id": 842,
    "created_at": "2023-05-02T19:39:06.000000Z",
    "updated_at": "2023-05-02T19:39:06.000000Z",
    "name": "Maribojoc",
    "code": "0701232000",
    "zip_code": "",
    "district": "Lone",
    "type": "Mun",
    "region_id": 8,
    "province_id": 39
  },
  {
    "id": 843,
    "created_at": "2023-05-02T19:39:06.000000Z",
    "updated_at": "2023-05-02T19:39:06.000000Z",
    "name": "Panglao",
    "code": "0701233000",
    "zip_code": "",
    "district": "Lone",
    "type": "Mun",
    "region_id": 8,
    "province_id": 39
  },
  {
    "id": 844,
    "created_at": "2023-05-02T19:39:06.000000Z",
    "updated_at": "2023-05-02T19:39:06.000000Z",
    "name": "Pilar",
    "code": "0701234000",
    "zip_code": "",
    "district": "Lone",
    "type": "Mun",
    "region_id": 8,
    "province_id": 39
  },
  {
    "id": 845,
    "created_at": "2023-05-02T19:39:06.000000Z",
    "updated_at": "2023-05-02T19:39:06.000000Z",
    "name": "President Carlos P. Garcia",
    "code": "0701235000",
    "zip_code": "",
    "district": "Lone",
    "type": "Mun",
    "region_id": 8,
    "province_id": 39
  },
  {
    "id": 846,
    "created_at": "2023-05-02T19:39:06.000000Z",
    "updated_at": "2023-05-02T19:39:06.000000Z",
    "name": "Sagbayan",
    "code": "0701236000",
    "zip_code": "",
    "district": "Lone",
    "type": "Mun",
    "region_id": 8,
    "province_id": 39
  },
  {
    "id": 847,
    "created_at": "2023-05-02T19:39:06.000000Z",
    "updated_at": "2023-05-02T19:39:06.000000Z",
    "name": "San Isidro",
    "code": "0701237000",
    "zip_code": "",
    "district": "Lone",
    "type": "Mun",
    "region_id": 8,
    "province_id": 39
  },
  {
    "id": 848,
    "created_at": "2023-05-02T19:39:06.000000Z",
    "updated_at": "2023-05-02T19:39:06.000000Z",
    "name": "San Miguel",
    "code": "0701238000",
    "zip_code": "",
    "district": "Lone",
    "type": "Mun",
    "region_id": 8,
    "province_id": 39
  },
  {
    "id": 849,
    "created_at": "2023-05-02T19:39:06.000000Z",
    "updated_at": "2023-05-02T19:39:06.000000Z",
    "name": "Sevilla",
    "code": "0701239000",
    "zip_code": "",
    "district": "Lone",
    "type": "Mun",
    "region_id": 8,
    "province_id": 39
  },
  {
    "id": 850,
    "created_at": "2023-05-02T19:39:06.000000Z",
    "updated_at": "2023-05-02T19:39:06.000000Z",
    "name": "Sierra Bullones",
    "code": "0701240000",
    "zip_code": "",
    "district": "Lone",
    "type": "Mun",
    "region_id": 8,
    "province_id": 39
  },
  {
    "id": 851,
    "created_at": "2023-05-02T19:39:06.000000Z",
    "updated_at": "2023-05-02T19:39:06.000000Z",
    "name": "Sikatuna",
    "code": "0701241000",
    "zip_code": "",
    "district": "Lone",
    "type": "Mun",
    "region_id": 8,
    "province_id": 39
  },
  {
    "id": 852,
    "created_at": "2023-05-02T19:39:06.000000Z",
    "updated_at": "2023-05-02T19:39:06.000000Z",
    "name": "City of Tagbilaran ",
    "code": "0701242000",
    "zip_code": "",
    "district": "Lone",
    "type": "City",
    "region_id": 8,
    "province_id": 39
  },
  {
    "id": 853,
    "created_at": "2023-05-02T19:39:06.000000Z",
    "updated_at": "2023-05-02T19:39:06.000000Z",
    "name": "Talibon",
    "code": "0701243000",
    "zip_code": "",
    "district": "Lone",
    "type": "Mun",
    "region_id": 8,
    "province_id": 39
  },
  {
    "id": 854,
    "created_at": "2023-05-02T19:39:06.000000Z",
    "updated_at": "2023-05-02T19:39:06.000000Z",
    "name": "Trinidad",
    "code": "0701244000",
    "zip_code": "",
    "district": "Lone",
    "type": "Mun",
    "region_id": 8,
    "province_id": 39
  },
  {
    "id": 855,
    "created_at": "2023-05-02T19:39:06.000000Z",
    "updated_at": "2023-05-02T19:39:06.000000Z",
    "name": "Tubigon",
    "code": "0701245000",
    "zip_code": "",
    "district": "Lone",
    "type": "Mun",
    "region_id": 8,
    "province_id": 39
  },
  {
    "id": 856,
    "created_at": "2023-05-02T19:39:06.000000Z",
    "updated_at": "2023-05-02T19:39:06.000000Z",
    "name": "Ubay",
    "code": "0701246000",
    "zip_code": "",
    "district": "Lone",
    "type": "Mun",
    "region_id": 8,
    "province_id": 39
  },
  {
    "id": 857,
    "created_at": "2023-05-02T19:39:06.000000Z",
    "updated_at": "2023-05-02T19:39:06.000000Z",
    "name": "Valencia",
    "code": "0701247000",
    "zip_code": "",
    "district": "Lone",
    "type": "Mun",
    "region_id": 8,
    "province_id": 39
  },
  {
    "id": 858,
    "created_at": "2023-05-02T19:39:06.000000Z",
    "updated_at": "2023-05-02T19:39:06.000000Z",
    "name": "Bien Unido",
    "code": "0701248000",
    "zip_code": "",
    "district": "Lone",
    "type": "Mun",
    "region_id": 8,
    "province_id": 39
  },
  {
    "id": 859,
    "created_at": "2023-05-02T19:39:06.000000Z",
    "updated_at": "2023-05-02T19:39:06.000000Z",
    "name": "Alcantara",
    "code": "0702201000",
    "zip_code": "",
    "district": "Lone",
    "type": "Mun",
    "region_id": 8,
    "province_id": 40
  },
  {
    "id": 860,
    "created_at": "2023-05-02T19:39:06.000000Z",
    "updated_at": "2023-05-02T19:39:06.000000Z",
    "name": "Alcoy",
    "code": "0702202000",
    "zip_code": "",
    "district": "Lone",
    "type": "Mun",
    "region_id": 8,
    "province_id": 40
  },
  {
    "id": 861,
    "created_at": "2023-05-02T19:39:06.000000Z",
    "updated_at": "2023-05-02T19:39:06.000000Z",
    "name": "Alegria",
    "code": "0702203000",
    "zip_code": "",
    "district": "Lone",
    "type": "Mun",
    "region_id": 8,
    "province_id": 40
  },
  {
    "id": 862,
    "created_at": "2023-05-02T19:39:06.000000Z",
    "updated_at": "2023-05-02T19:39:06.000000Z",
    "name": "Aloguinsan",
    "code": "0702204000",
    "zip_code": "",
    "district": "Lone",
    "type": "Mun",
    "region_id": 8,
    "province_id": 40
  },
  {
    "id": 863,
    "created_at": "2023-05-02T19:39:06.000000Z",
    "updated_at": "2023-05-02T19:39:06.000000Z",
    "name": "Argao",
    "code": "0702205000",
    "zip_code": "",
    "district": "Lone",
    "type": "Mun",
    "region_id": 8,
    "province_id": 40
  },
  {
    "id": 864,
    "created_at": "2023-05-02T19:39:06.000000Z",
    "updated_at": "2023-05-02T19:39:06.000000Z",
    "name": "Asturias",
    "code": "0702206000",
    "zip_code": "",
    "district": "Lone",
    "type": "Mun",
    "region_id": 8,
    "province_id": 40
  },
  {
    "id": 865,
    "created_at": "2023-05-02T19:39:06.000000Z",
    "updated_at": "2023-05-02T19:39:06.000000Z",
    "name": "Badian",
    "code": "0702207000",
    "zip_code": "",
    "district": "Lone",
    "type": "Mun",
    "region_id": 8,
    "province_id": 40
  },
  {
    "id": 866,
    "created_at": "2023-05-02T19:39:06.000000Z",
    "updated_at": "2023-05-02T19:39:06.000000Z",
    "name": "Balamban",
    "code": "0702208000",
    "zip_code": "",
    "district": "Lone",
    "type": "Mun",
    "region_id": 8,
    "province_id": 40
  },
  {
    "id": 867,
    "created_at": "2023-05-02T19:39:06.000000Z",
    "updated_at": "2023-05-02T19:39:06.000000Z",
    "name": "Bantayan",
    "code": "0702209000",
    "zip_code": "",
    "district": "Lone",
    "type": "Mun",
    "region_id": 8,
    "province_id": 40
  },
  {
    "id": 868,
    "created_at": "2023-05-02T19:39:06.000000Z",
    "updated_at": "2023-05-02T19:39:06.000000Z",
    "name": "Barili",
    "code": "0702210000",
    "zip_code": "",
    "district": "Lone",
    "type": "Mun",
    "region_id": 8,
    "province_id": 40
  },
  {
    "id": 869,
    "created_at": "2023-05-02T19:39:06.000000Z",
    "updated_at": "2023-05-02T19:39:06.000000Z",
    "name": "City of Bogo",
    "code": "0702211000",
    "zip_code": "",
    "district": "Lone",
    "type": "City",
    "region_id": 8,
    "province_id": 40
  },
  {
    "id": 870,
    "created_at": "2023-05-02T19:39:07.000000Z",
    "updated_at": "2023-05-02T19:39:07.000000Z",
    "name": "Boljoon",
    "code": "0702212000",
    "zip_code": "",
    "district": "Lone",
    "type": "Mun",
    "region_id": 8,
    "province_id": 40
  },
  {
    "id": 871,
    "created_at": "2023-05-02T19:39:07.000000Z",
    "updated_at": "2023-05-02T19:39:07.000000Z",
    "name": "Borbon",
    "code": "0702213000",
    "zip_code": "",
    "district": "Lone",
    "type": "Mun",
    "region_id": 8,
    "province_id": 40
  },
  {
    "id": 872,
    "created_at": "2023-05-02T19:39:07.000000Z",
    "updated_at": "2023-05-02T19:39:07.000000Z",
    "name": "City of Carcar",
    "code": "0702214000",
    "zip_code": "",
    "district": "Lone",
    "type": "City",
    "region_id": 8,
    "province_id": 40
  },
  {
    "id": 873,
    "created_at": "2023-05-02T19:39:07.000000Z",
    "updated_at": "2023-05-02T19:39:07.000000Z",
    "name": "Carmen",
    "code": "0702215000",
    "zip_code": "",
    "district": "Lone",
    "type": "Mun",
    "region_id": 8,
    "province_id": 40
  },
  {
    "id": 874,
    "created_at": "2023-05-02T19:39:07.000000Z",
    "updated_at": "2023-05-02T19:39:07.000000Z",
    "name": "Catmon",
    "code": "0702216000",
    "zip_code": "",
    "district": "Lone",
    "type": "Mun",
    "region_id": 8,
    "province_id": 40
  },
  {
    "id": 875,
    "created_at": "2023-05-02T19:39:07.000000Z",
    "updated_at": "2023-05-02T19:39:07.000000Z",
    "name": "City of Cebu ",
    "code": "0730600000",
    "zip_code": "",
    "district": "Lone",
    "type": "City",
    "region_id": 8,
    "province_id": 40
  },
  {
    "id": 876,
    "created_at": "2023-05-02T19:39:07.000000Z",
    "updated_at": "2023-05-02T19:39:07.000000Z",
    "name": "Compostela",
    "code": "0702218000",
    "zip_code": "",
    "district": "Lone",
    "type": "Mun",
    "region_id": 8,
    "province_id": 40
  },
  {
    "id": 877,
    "created_at": "2023-05-02T19:39:07.000000Z",
    "updated_at": "2023-05-02T19:39:07.000000Z",
    "name": "Consolacion",
    "code": "0702219000",
    "zip_code": "",
    "district": "Lone",
    "type": "Mun",
    "region_id": 8,
    "province_id": 40
  },
  {
    "id": 878,
    "created_at": "2023-05-02T19:39:07.000000Z",
    "updated_at": "2023-05-02T19:39:07.000000Z",
    "name": "Cordova",
    "code": "0702220000",
    "zip_code": "",
    "district": "Lone",
    "type": "Mun",
    "region_id": 8,
    "province_id": 40
  },
  {
    "id": 879,
    "created_at": "2023-05-02T19:39:07.000000Z",
    "updated_at": "2023-05-02T19:39:07.000000Z",
    "name": "Daanbantayan",
    "code": "0702221000",
    "zip_code": "",
    "district": "Lone",
    "type": "Mun",
    "region_id": 8,
    "province_id": 40
  },
  {
    "id": 880,
    "created_at": "2023-05-02T19:39:07.000000Z",
    "updated_at": "2023-05-02T19:39:07.000000Z",
    "name": "Dalaguete",
    "code": "0702222000",
    "zip_code": "",
    "district": "Lone",
    "type": "Mun",
    "region_id": 8,
    "province_id": 40
  },
  {
    "id": 881,
    "created_at": "2023-05-02T19:39:07.000000Z",
    "updated_at": "2023-05-02T19:39:07.000000Z",
    "name": "Danao City",
    "code": "0702223000",
    "zip_code": "",
    "district": "Lone",
    "type": "City",
    "region_id": 8,
    "province_id": 40
  },
  {
    "id": 882,
    "created_at": "2023-05-02T19:39:07.000000Z",
    "updated_at": "2023-05-02T19:39:07.000000Z",
    "name": "Dumanjug",
    "code": "0702224000",
    "zip_code": "",
    "district": "Lone",
    "type": "Mun",
    "region_id": 8,
    "province_id": 40
  },
  {
    "id": 883,
    "created_at": "2023-05-02T19:39:07.000000Z",
    "updated_at": "2023-05-02T19:39:07.000000Z",
    "name": "Ginatilan",
    "code": "0702225000",
    "zip_code": "",
    "district": "Lone",
    "type": "Mun",
    "region_id": 8,
    "province_id": 40
  },
  {
    "id": 884,
    "created_at": "2023-05-02T19:39:07.000000Z",
    "updated_at": "2023-05-02T19:39:07.000000Z",
    "name": "City of Lapu-Lapu",
    "code": "0731100000",
    "zip_code": "",
    "district": "Lone",
    "type": "City",
    "region_id": 8,
    "province_id": 40
  },
  {
    "id": 885,
    "created_at": "2023-05-02T19:39:07.000000Z",
    "updated_at": "2023-05-02T19:39:07.000000Z",
    "name": "Liloan",
    "code": "0702227000",
    "zip_code": "",
    "district": "Lone",
    "type": "Mun",
    "region_id": 8,
    "province_id": 40
  },
  {
    "id": 886,
    "created_at": "2023-05-02T19:39:07.000000Z",
    "updated_at": "2023-05-02T19:39:07.000000Z",
    "name": "Madridejos",
    "code": "0702228000",
    "zip_code": "",
    "district": "Lone",
    "type": "Mun",
    "region_id": 8,
    "province_id": 40
  },
  {
    "id": 887,
    "created_at": "2023-05-02T19:39:07.000000Z",
    "updated_at": "2023-05-02T19:39:07.000000Z",
    "name": "Malabuyoc",
    "code": "0702229000",
    "zip_code": "",
    "district": "Lone",
    "type": "Mun",
    "region_id": 8,
    "province_id": 40
  },
  {
    "id": 888,
    "created_at": "2023-05-02T19:39:07.000000Z",
    "updated_at": "2023-05-02T19:39:07.000000Z",
    "name": "City of Mandaue",
    "code": "0731300000",
    "zip_code": "",
    "district": "Lone",
    "type": "City",
    "region_id": 8,
    "province_id": 40
  },
  {
    "id": 889,
    "created_at": "2023-05-02T19:39:07.000000Z",
    "updated_at": "2023-05-02T19:39:07.000000Z",
    "name": "Medellin",
    "code": "0702231000",
    "zip_code": "",
    "district": "Lone",
    "type": "Mun",
    "region_id": 8,
    "province_id": 40
  },
  {
    "id": 890,
    "created_at": "2023-05-02T19:39:07.000000Z",
    "updated_at": "2023-05-02T19:39:07.000000Z",
    "name": "Minglanilla",
    "code": "0702232000",
    "zip_code": "",
    "district": "Lone",
    "type": "Mun",
    "region_id": 8,
    "province_id": 40
  },
  {
    "id": 891,
    "created_at": "2023-05-02T19:39:07.000000Z",
    "updated_at": "2023-05-02T19:39:07.000000Z",
    "name": "Moalboal",
    "code": "0702233000",
    "zip_code": "",
    "district": "Lone",
    "type": "Mun",
    "region_id": 8,
    "province_id": 40
  },
  {
    "id": 892,
    "created_at": "2023-05-02T19:39:07.000000Z",
    "updated_at": "2023-05-02T19:39:07.000000Z",
    "name": "City of Naga",
    "code": "0702234000",
    "zip_code": "",
    "district": "Lone",
    "type": "City",
    "region_id": 8,
    "province_id": 40
  },
  {
    "id": 893,
    "created_at": "2023-05-02T19:39:07.000000Z",
    "updated_at": "2023-05-02T19:39:07.000000Z",
    "name": "Oslob",
    "code": "0702235000",
    "zip_code": "",
    "district": "Lone",
    "type": "Mun",
    "region_id": 8,
    "province_id": 40
  },
  {
    "id": 894,
    "created_at": "2023-05-02T19:39:07.000000Z",
    "updated_at": "2023-05-02T19:39:07.000000Z",
    "name": "Pilar",
    "code": "0702236000",
    "zip_code": "",
    "district": "Lone",
    "type": "Mun",
    "region_id": 8,
    "province_id": 40
  },
  {
    "id": 895,
    "created_at": "2023-05-02T19:39:07.000000Z",
    "updated_at": "2023-05-02T19:39:07.000000Z",
    "name": "Pinamungajan",
    "code": "0702237000",
    "zip_code": "",
    "district": "Lone",
    "type": "Mun",
    "region_id": 8,
    "province_id": 40
  },
  {
    "id": 896,
    "created_at": "2023-05-02T19:39:07.000000Z",
    "updated_at": "2023-05-02T19:39:07.000000Z",
    "name": "Poro",
    "code": "0702238000",
    "zip_code": "",
    "district": "Lone",
    "type": "Mun",
    "region_id": 8,
    "province_id": 40
  },
  {
    "id": 897,
    "created_at": "2023-05-02T19:39:07.000000Z",
    "updated_at": "2023-05-02T19:39:07.000000Z",
    "name": "Ronda",
    "code": "0702239000",
    "zip_code": "",
    "district": "Lone",
    "type": "Mun",
    "region_id": 8,
    "province_id": 40
  },
  {
    "id": 898,
    "created_at": "2023-05-02T19:39:07.000000Z",
    "updated_at": "2023-05-02T19:39:07.000000Z",
    "name": "Samboan",
    "code": "0702240000",
    "zip_code": "",
    "district": "Lone",
    "type": "Mun",
    "region_id": 8,
    "province_id": 40
  },
  {
    "id": 899,
    "created_at": "2023-05-02T19:39:07.000000Z",
    "updated_at": "2023-05-02T19:39:07.000000Z",
    "name": "San Fernando",
    "code": "0702241000",
    "zip_code": "",
    "district": "Lone",
    "type": "Mun",
    "region_id": 8,
    "province_id": 40
  },
  {
    "id": 900,
    "created_at": "2023-05-02T19:39:07.000000Z",
    "updated_at": "2023-05-02T19:39:07.000000Z",
    "name": "San Francisco",
    "code": "0702242000",
    "zip_code": "",
    "district": "Lone",
    "type": "Mun",
    "region_id": 8,
    "province_id": 40
  },
  {
    "id": 901,
    "created_at": "2023-05-02T19:39:07.000000Z",
    "updated_at": "2023-05-02T19:39:07.000000Z",
    "name": "San Remigio",
    "code": "0702243000",
    "zip_code": "",
    "district": "Lone",
    "type": "Mun",
    "region_id": 8,
    "province_id": 40
  },
  {
    "id": 902,
    "created_at": "2023-05-02T19:39:07.000000Z",
    "updated_at": "2023-05-02T19:39:07.000000Z",
    "name": "Santa Fe",
    "code": "0702244000",
    "zip_code": "",
    "district": "Lone",
    "type": "Mun",
    "region_id": 8,
    "province_id": 40
  },
  {
    "id": 903,
    "created_at": "2023-05-02T19:39:07.000000Z",
    "updated_at": "2023-05-02T19:39:07.000000Z",
    "name": "Santander",
    "code": "0702245000",
    "zip_code": "",
    "district": "Lone",
    "type": "Mun",
    "region_id": 8,
    "province_id": 40
  },
  {
    "id": 904,
    "created_at": "2023-05-02T19:39:07.000000Z",
    "updated_at": "2023-05-02T19:39:07.000000Z",
    "name": "Sibonga",
    "code": "0702246000",
    "zip_code": "",
    "district": "Lone",
    "type": "Mun",
    "region_id": 8,
    "province_id": 40
  },
  {
    "id": 905,
    "created_at": "2023-05-02T19:39:07.000000Z",
    "updated_at": "2023-05-02T19:39:07.000000Z",
    "name": "Sogod",
    "code": "0702247000",
    "zip_code": "",
    "district": "Lone",
    "type": "Mun",
    "region_id": 8,
    "province_id": 40
  },
  {
    "id": 906,
    "created_at": "2023-05-02T19:39:07.000000Z",
    "updated_at": "2023-05-02T19:39:07.000000Z",
    "name": "Tabogon",
    "code": "0702248000",
    "zip_code": "",
    "district": "Lone",
    "type": "Mun",
    "region_id": 8,
    "province_id": 40
  },
  {
    "id": 907,
    "created_at": "2023-05-02T19:39:08.000000Z",
    "updated_at": "2023-05-02T19:39:08.000000Z",
    "name": "Tabuelan",
    "code": "0702249000",
    "zip_code": "",
    "district": "Lone",
    "type": "Mun",
    "region_id": 8,
    "province_id": 40
  },
  {
    "id": 908,
    "created_at": "2023-05-02T19:39:08.000000Z",
    "updated_at": "2023-05-02T19:39:08.000000Z",
    "name": "City of Talisay",
    "code": "0702250000",
    "zip_code": "",
    "district": "Lone",
    "type": "City",
    "region_id": 8,
    "province_id": 40
  },
  {
    "id": 909,
    "created_at": "2023-05-02T19:39:08.000000Z",
    "updated_at": "2023-05-02T19:39:08.000000Z",
    "name": "City of Toledo",
    "code": "0702251000",
    "zip_code": "",
    "district": "Lone",
    "type": "City",
    "region_id": 8,
    "province_id": 40
  },
  {
    "id": 910,
    "created_at": "2023-05-02T19:39:08.000000Z",
    "updated_at": "2023-05-02T19:39:08.000000Z",
    "name": "Tuburan",
    "code": "0702252000",
    "zip_code": "",
    "district": "Lone",
    "type": "Mun",
    "region_id": 8,
    "province_id": 40
  },
  {
    "id": 911,
    "created_at": "2023-05-02T19:39:08.000000Z",
    "updated_at": "2023-05-02T19:39:08.000000Z",
    "name": "Tudela",
    "code": "0702253000",
    "zip_code": "",
    "district": "Lone",
    "type": "Mun",
    "region_id": 8,
    "province_id": 40
  },
  {
    "id": 912,
    "created_at": "2023-05-02T19:39:08.000000Z",
    "updated_at": "2023-05-02T19:39:08.000000Z",
    "name": "Amlan",
    "code": "0704601000",
    "zip_code": "",
    "district": "Lone",
    "type": "Mun",
    "region_id": 8,
    "province_id": 41
  },
  {
    "id": 913,
    "created_at": "2023-05-02T19:39:08.000000Z",
    "updated_at": "2023-05-02T19:39:08.000000Z",
    "name": "Ayungon",
    "code": "0704602000",
    "zip_code": "",
    "district": "Lone",
    "type": "Mun",
    "region_id": 8,
    "province_id": 41
  },
  {
    "id": 914,
    "created_at": "2023-05-02T19:39:08.000000Z",
    "updated_at": "2023-05-02T19:39:08.000000Z",
    "name": "Bacong",
    "code": "0704603000",
    "zip_code": "",
    "district": "Lone",
    "type": "Mun",
    "region_id": 8,
    "province_id": 41
  },
  {
    "id": 915,
    "created_at": "2023-05-02T19:39:08.000000Z",
    "updated_at": "2023-05-02T19:39:08.000000Z",
    "name": "City of Bais",
    "code": "0704604000",
    "zip_code": "",
    "district": "Lone",
    "type": "City",
    "region_id": 8,
    "province_id": 41
  },
  {
    "id": 916,
    "created_at": "2023-05-02T19:39:08.000000Z",
    "updated_at": "2023-05-02T19:39:08.000000Z",
    "name": "Basay",
    "code": "0704605000",
    "zip_code": "",
    "district": "Lone",
    "type": "Mun",
    "region_id": 8,
    "province_id": 41
  },
  {
    "id": 917,
    "created_at": "2023-05-02T19:39:08.000000Z",
    "updated_at": "2023-05-02T19:39:08.000000Z",
    "name": "City of Bayawan",
    "code": "0704606000",
    "zip_code": "",
    "district": "Lone",
    "type": "City",
    "region_id": 8,
    "province_id": 41
  },
  {
    "id": 918,
    "created_at": "2023-05-02T19:39:08.000000Z",
    "updated_at": "2023-05-02T19:39:08.000000Z",
    "name": "Bindoy",
    "code": "0704607000",
    "zip_code": "",
    "district": "Lone",
    "type": "Mun",
    "region_id": 8,
    "province_id": 41
  },
  {
    "id": 919,
    "created_at": "2023-05-02T19:39:08.000000Z",
    "updated_at": "2023-05-02T19:39:08.000000Z",
    "name": "City of Canlaon",
    "code": "0704608000",
    "zip_code": "",
    "district": "Lone",
    "type": "City",
    "region_id": 8,
    "province_id": 41
  },
  {
    "id": 920,
    "created_at": "2023-05-02T19:39:08.000000Z",
    "updated_at": "2023-05-02T19:39:08.000000Z",
    "name": "Dauin",
    "code": "0704609000",
    "zip_code": "",
    "district": "Lone",
    "type": "Mun",
    "region_id": 8,
    "province_id": 41
  },
  {
    "id": 921,
    "created_at": "2023-05-02T19:39:08.000000Z",
    "updated_at": "2023-05-02T19:39:08.000000Z",
    "name": "City of Dumaguete ",
    "code": "0704610000",
    "zip_code": "",
    "district": "Lone",
    "type": "City",
    "region_id": 8,
    "province_id": 41
  },
  {
    "id": 922,
    "created_at": "2023-05-02T19:39:08.000000Z",
    "updated_at": "2023-05-02T19:39:08.000000Z",
    "name": "City of Guihulngan",
    "code": "0704611000",
    "zip_code": "",
    "district": "Lone",
    "type": "City",
    "region_id": 8,
    "province_id": 41
  },
  {
    "id": 923,
    "created_at": "2023-05-02T19:39:08.000000Z",
    "updated_at": "2023-05-02T19:39:08.000000Z",
    "name": "Jimalalud",
    "code": "0704612000",
    "zip_code": "",
    "district": "Lone",
    "type": "Mun",
    "region_id": 8,
    "province_id": 41
  },
  {
    "id": 924,
    "created_at": "2023-05-02T19:39:08.000000Z",
    "updated_at": "2023-05-02T19:39:08.000000Z",
    "name": "La Libertad",
    "code": "0704613000",
    "zip_code": "",
    "district": "Lone",
    "type": "Mun",
    "region_id": 8,
    "province_id": 41
  },
  {
    "id": 925,
    "created_at": "2023-05-02T19:39:08.000000Z",
    "updated_at": "2023-05-02T19:39:08.000000Z",
    "name": "Mabinay",
    "code": "0704614000",
    "zip_code": "",
    "district": "Lone",
    "type": "Mun",
    "region_id": 8,
    "province_id": 41
  },
  {
    "id": 926,
    "created_at": "2023-05-02T19:39:08.000000Z",
    "updated_at": "2023-05-02T19:39:08.000000Z",
    "name": "Manjuyod",
    "code": "0704615000",
    "zip_code": "",
    "district": "Lone",
    "type": "Mun",
    "region_id": 8,
    "province_id": 41
  },
  {
    "id": 927,
    "created_at": "2023-05-02T19:39:08.000000Z",
    "updated_at": "2023-05-02T19:39:08.000000Z",
    "name": "Pamplona",
    "code": "0704616000",
    "zip_code": "",
    "district": "Lone",
    "type": "Mun",
    "region_id": 8,
    "province_id": 41
  },
  {
    "id": 928,
    "created_at": "2023-05-02T19:39:08.000000Z",
    "updated_at": "2023-05-02T19:39:08.000000Z",
    "name": "San Jose",
    "code": "0704617000",
    "zip_code": "",
    "district": "Lone",
    "type": "Mun",
    "region_id": 8,
    "province_id": 41
  },
  {
    "id": 929,
    "created_at": "2023-05-02T19:39:08.000000Z",
    "updated_at": "2023-05-02T19:39:08.000000Z",
    "name": "Santa Catalina",
    "code": "0704618000",
    "zip_code": "",
    "district": "Lone",
    "type": "Mun",
    "region_id": 8,
    "province_id": 41
  },
  {
    "id": 930,
    "created_at": "2023-05-02T19:39:08.000000Z",
    "updated_at": "2023-05-02T19:39:08.000000Z",
    "name": "Siaton",
    "code": "0704619000",
    "zip_code": "",
    "district": "Lone",
    "type": "Mun",
    "region_id": 8,
    "province_id": 41
  },
  {
    "id": 931,
    "created_at": "2023-05-02T19:39:08.000000Z",
    "updated_at": "2023-05-02T19:39:08.000000Z",
    "name": "Sibulan",
    "code": "0704620000",
    "zip_code": "",
    "district": "Lone",
    "type": "Mun",
    "region_id": 8,
    "province_id": 41
  },
  {
    "id": 932,
    "created_at": "2023-05-02T19:39:08.000000Z",
    "updated_at": "2023-05-02T19:39:08.000000Z",
    "name": "City of Tanjay",
    "code": "0704621000",
    "zip_code": "",
    "district": "Lone",
    "type": "City",
    "region_id": 8,
    "province_id": 41
  },
  {
    "id": 933,
    "created_at": "2023-05-02T19:39:08.000000Z",
    "updated_at": "2023-05-02T19:39:08.000000Z",
    "name": "Tayasan",
    "code": "0704622000",
    "zip_code": "",
    "district": "Lone",
    "type": "Mun",
    "region_id": 8,
    "province_id": 41
  },
  {
    "id": 934,
    "created_at": "2023-05-02T19:39:08.000000Z",
    "updated_at": "2023-05-02T19:39:08.000000Z",
    "name": "Valencia",
    "code": "0704623000",
    "zip_code": "",
    "district": "Lone",
    "type": "Mun",
    "region_id": 8,
    "province_id": 41
  },
  {
    "id": 935,
    "created_at": "2023-05-02T19:39:08.000000Z",
    "updated_at": "2023-05-02T19:39:08.000000Z",
    "name": "Vallehermoso",
    "code": "0704624000",
    "zip_code": "",
    "district": "Lone",
    "type": "Mun",
    "region_id": 8,
    "province_id": 41
  },
  {
    "id": 936,
    "created_at": "2023-05-02T19:39:08.000000Z",
    "updated_at": "2023-05-02T19:39:08.000000Z",
    "name": "Zamboanguita",
    "code": "0704625000",
    "zip_code": "",
    "district": "Lone",
    "type": "Mun",
    "region_id": 8,
    "province_id": 41
  },
  {
    "id": 937,
    "created_at": "2023-05-02T19:39:08.000000Z",
    "updated_at": "2023-05-02T19:39:08.000000Z",
    "name": "Enrique Villanueva",
    "code": "0706101000",
    "zip_code": "",
    "district": "Lone",
    "type": "Mun",
    "region_id": 8,
    "province_id": 42
  },
  {
    "id": 938,
    "created_at": "2023-05-02T19:39:08.000000Z",
    "updated_at": "2023-05-02T19:39:08.000000Z",
    "name": "Larena",
    "code": "0706102000",
    "zip_code": "",
    "district": "Lone",
    "type": "Mun",
    "region_id": 8,
    "province_id": 42
  },
  {
    "id": 939,
    "created_at": "2023-05-02T19:39:08.000000Z",
    "updated_at": "2023-05-02T19:39:08.000000Z",
    "name": "Lazi",
    "code": "0706103000",
    "zip_code": "",
    "district": "Lone",
    "type": "Mun",
    "region_id": 8,
    "province_id": 42
  },
  {
    "id": 940,
    "created_at": "2023-05-02T19:39:08.000000Z",
    "updated_at": "2023-05-02T19:39:08.000000Z",
    "name": "Maria",
    "code": "0706104000",
    "zip_code": "",
    "district": "Lone",
    "type": "Mun",
    "region_id": 8,
    "province_id": 42
  },
  {
    "id": 941,
    "created_at": "2023-05-02T19:39:08.000000Z",
    "updated_at": "2023-05-02T19:39:08.000000Z",
    "name": "San Juan",
    "code": "0706105000",
    "zip_code": "",
    "district": "Lone",
    "type": "Mun",
    "region_id": 8,
    "province_id": 42
  },
  {
    "id": 942,
    "created_at": "2023-05-02T19:39:08.000000Z",
    "updated_at": "2023-05-02T19:39:08.000000Z",
    "name": "Siquijor ",
    "code": "0706106000",
    "zip_code": "",
    "district": "Lone",
    "type": "Mun",
    "region_id": 8,
    "province_id": 42
  }
]